<?xml version="1.0" encoding="UTF-8"?>
<con:soapui-project id="81ad049a-8067-476d-ab02-a62c656e34de" activeEnvironment="Default" name="MS_MonitoringDemo" resourceRoot="" soapui-version="5.7.0" abortOnError="false" runType="SEQUENTIAL" xmlns:con="http://eviware.com/soapui/config"><con:settings/><con:interface xsi:type="con:RestService" id="1659179f-eefb-468f-b518-ca3adaae7a64" wadlVersion="http://wadl.dev.java.net/2009/02" name="http://momitoring-exp-web.uk-e1.cloudhub.io" type="rest" xmlns:xsi="http://www.w3.org/2001/XMLSchema-instance"><con:settings/><con:definitionCache type="TEXT" rootPart=""/><con:endpoints><con:endpoint>http://momitoring-exp-web.uk-e1.cloudhub.io</con:endpoint></con:endpoints><con:resource name="GetCustomer" path="/api/getCustomer" id="287845dc-df3e-4808-b46d-55410f4081e5"><con:settings/><con:parameters><con:parameter><con:name>customerId</con:name><con:value>1</con:value><con:style>QUERY</con:style><con:default>1</con:default><con:path xsi:nil="true"/><con:description xsi:nil="true"/></con:parameter></con:parameters><con:method name="WEB GetCustomer OK" id="f04cdc83-bd97-494c-a97f-557f6850af5b" method="GET"><con:settings/><con:parameters/><con:representation type="FAULT"><con:mediaType>application/json; charset=UTF-8</con:mediaType><con:status>401</con:status><con:params/><con:element xmlns:get="http://momitoring-exp-web.uk-e1.cloudhub.io/api/getCustomer">get:Fault</con:element></con:representation><con:representation type="RESPONSE"><con:mediaType>application/json</con:mediaType><con:status>200</con:status><con:params/><con:element>Response</con:element></con:representation><con:representation type="FAULT"><con:mediaType xsi:nil="true"/><con:status>500</con:status><con:params/><con:element>data</con:element></con:representation><con:representation type="FAULT"><con:mediaType xsi:nil="true"/><con:status>500</con:status><con:params/><con:element>data</con:element></con:representation><con:request name="WEB getCustomer" id="b97181b3-72d9-4d00-adf1-712b6d263453" mediaType="application/json"><con:settings><con:setting id="com.eviware.soapui.impl.wsdl.WsdlRequest@request-headers">&lt;xml-fragment xmlns:con="http://eviware.com/soapui/config">
  &lt;con:entry key="client_id" value="cd7e0e068666431880782b9f035fbc4f"/>
  &lt;con:entry key="client_secret" value="dFb3274f253a4cbC8d5Ce0063a220fCe"/>
&lt;/xml-fragment></con:setting></con:settings><con:endpoint>http://momitoring-exp-web.uk-e1.cloudhub.io</con:endpoint><con:request/><con:originalUri>http://momitoring-exp-web.uk-e1.cloudhub.io/api/getCustomer</con:originalUri><con:credentials><con:authType>No Authorization</con:authType></con:credentials><con:jmsConfig JMSDeliveryMode="PERSISTENT"/><con:jmsPropertyConfig/><con:parameters><entry key="customerId" value="1" xmlns="http://eviware.com/soapui/config"/></con:parameters><con:parameterOrder><con:entry>customerId</con:entry></con:parameterOrder></con:request><con:request name="WEB Partner getCustomer" id="b97181b3-72d9-4d00-adf1-712b6d263453" mediaType="application/json"><con:settings><con:setting id="com.eviware.soapui.impl.wsdl.WsdlRequest@request-headers">&lt;xml-fragment xmlns:con="http://eviware.com/soapui/config">
  &lt;con:entry key="client_id" value="92cdc1daf4fa490fb8b215348f583fb0"/>
  &lt;con:entry key="client_secret" value="c3763342Ad724D54ba828f530803EE86"/>
&lt;/xml-fragment></con:setting></con:settings><con:endpoint>http://momitoring-exp-web.uk-e1.cloudhub.io</con:endpoint><con:request/><con:originalUri>http://momitoring-exp-web.uk-e1.cloudhub.io/api/getCustomer</con:originalUri><con:credentials><con:authType>No Authorization</con:authType></con:credentials><con:jmsConfig JMSDeliveryMode="PERSISTENT"/><con:jmsPropertyConfig/><con:parameters><entry key="customerId" value="1" xmlns="http://eviware.com/soapui/config"/></con:parameters><con:parameterOrder><con:entry>customerId</con:entry></con:parameterOrder></con:request><con:request name="WEB Partner getCustomer ERROR" id="b97181b3-72d9-4d00-adf1-712b6d263453" mediaType="application/json"><con:settings><con:setting id="com.eviware.soapui.impl.wsdl.WsdlRequest@request-headers">&lt;xml-fragment xmlns:con="http://eviware.com/soapui/config">
  &lt;con:entry key="client_id" value="92cdc1daf4fa490fb8b215348f583fb0"/>
  &lt;con:entry key="client_secret" value="c3763342Ad724D54ba828f530803EE86"/>
&lt;/xml-fragment></con:setting></con:settings><con:endpoint>http://momitoring-exp-web.uk-e1.cloudhub.io</con:endpoint><con:request/><con:originalUri>http://momitoring-exp-web.uk-e1.cloudhub.io/api/getCustomer</con:originalUri><con:credentials><con:authType>No Authorization</con:authType></con:credentials><con:jmsConfig JMSDeliveryMode="PERSISTENT"/><con:jmsPropertyConfig/><con:parameters><entry key="customerId" value="ccc" xmlns="http://eviware.com/soapui/config"/></con:parameters><con:parameterOrder><con:entry>customerId</con:entry></con:parameterOrder></con:request></con:method></con:resource></con:interface><con:interface xsi:type="con:RestService" id="36ab73f7-c656-4ce1-8734-0d1fc6afb04f" wadlVersion="http://wadl.dev.java.net/2009/02" name="http://monitoring-exp-partner.uk-e1.cloudhub.io" type="rest" xmlns:xsi="http://www.w3.org/2001/XMLSchema-instance"><con:settings/><con:definitionCache/><con:endpoints><con:endpoint>http://monitoring-exp-partner.uk-e1.cloudhub.io</con:endpoint></con:endpoints><con:resource name="GetCustomer" path="/api/getCustomer" id="710bec52-74cf-4cf4-a0de-5a2ecc708878"><con:settings/><con:parameters><con:parameter><con:name>customerId</con:name><con:value>1</con:value><con:style>QUERY</con:style><con:default>1</con:default><con:path xsi:nil="true"/><con:description xsi:nil="true"/></con:parameter></con:parameters><con:method name="PARTNER GetCustomer 1" id="2dffcaad-b8d9-4297-b125-118f91172057" method="GET"><con:settings/><con:parameters/><con:representation type="FAULT"><con:mediaType>application/json; charset=UTF-8</con:mediaType><con:status>401</con:status><con:params/><con:element xmlns:get="http://monitoring-exp-partner.uk-e1.cloudhub.io/api/getCustomer">get:Fault</con:element></con:representation><con:representation type="RESPONSE"><con:mediaType>application/json</con:mediaType><con:status>200</con:status><con:params/><con:element>Response</con:element></con:representation><con:representation type="FAULT"><con:mediaType xsi:nil="true"/><con:status>500</con:status><con:params/><con:element>data</con:element></con:representation><con:representation type="FAULT"><con:mediaType xsi:nil="true"/><con:status>500</con:status><con:params/><con:element>data</con:element></con:representation><con:representation type="FAULT"><con:mediaType xsi:nil="true"/><con:status>500</con:status><con:params/><con:element>data</con:element></con:representation><con:representation type="FAULT"><con:mediaType xsi:nil="true"/><con:status>500</con:status><con:params/><con:element>data</con:element></con:representation><con:representation type="FAULT"><con:mediaType xsi:nil="true"/><con:status>500</con:status><con:params/><con:element>data</con:element></con:representation><con:representation type="FAULT"><con:mediaType xsi:nil="true"/><con:status>500</con:status><con:params/><con:element>data</con:element></con:representation><con:request name="PARTNER Gold" id="45855003-36bb-4866-9205-c0e1a9114d6b" mediaType="application/json"><con:settings><con:setting id="com.eviware.soapui.impl.wsdl.WsdlRequest@request-headers">&lt;xml-fragment xmlns:con="http://eviware.com/soapui/config">
  &lt;con:entry key="client_id" value="e273a6fcccef4979b2afa4493c6e4c1e"/>
  &lt;con:entry key="client_secret" value="4250071BF60840DBbc5feCc8fB486b75"/>
&lt;/xml-fragment></con:setting></con:settings><con:endpoint>http://monitoring-exp-partner.uk-e1.cloudhub.io</con:endpoint><con:request/><con:originalUri>http://monitoring-exp-partner.uk-e1.cloudhub.io/api/getCustomer</con:originalUri><con:credentials><con:authType>No Authorization</con:authType></con:credentials><con:jmsConfig JMSDeliveryMode="PERSISTENT"/><con:jmsPropertyConfig/><con:parameters><entry key="customerId" value="1" xmlns="http://eviware.com/soapui/config"/></con:parameters><con:parameterOrder><con:entry>customerId</con:entry></con:parameterOrder></con:request><con:request name="PARTNER Free" id="45855003-36bb-4866-9205-c0e1a9114d6b" mediaType="application/json"><con:settings><con:setting id="com.eviware.soapui.impl.wsdl.WsdlRequest@request-headers">&lt;xml-fragment xmlns:con="http://eviware.com/soapui/config">
  &lt;con:entry key="client_id" value="05e34f7147f84d2cbab5f2d3004176c6"/>
  &lt;con:entry key="client_secret" value="22c30907f30045218f678738705F5B9A"/>
&lt;/xml-fragment></con:setting></con:settings><con:endpoint>http://monitoring-exp-partner.uk-e1.cloudhub.io</con:endpoint><con:request/><con:originalUri>http://monitoring-exp-partner.uk-e1.cloudhub.io/api/getCustomer</con:originalUri><con:credentials><con:authType>No Authorization</con:authType></con:credentials><con:jmsConfig JMSDeliveryMode="PERSISTENT"/><con:jmsPropertyConfig/><con:parameters><entry key="customerId" value="1" xmlns="http://eviware.com/soapui/config"/></con:parameters><con:parameterOrder><con:entry>customerId</con:entry></con:parameterOrder></con:request><con:request name="PARTNER New" id="45855003-36bb-4866-9205-c0e1a9114d6b" mediaType="application/json"><con:settings><con:setting id="com.eviware.soapui.impl.wsdl.WsdlRequest@request-headers">&lt;xml-fragment xmlns:con="http://eviware.com/soapui/config">
  &lt;con:entry key="client_id" value="f6d0574deabf4c5e909dbfbb99208ec8"/>
  &lt;con:entry key="client_secret" value="55640ba4007a466AaC7b49Db69E79aE3"/>
&lt;/xml-fragment></con:setting></con:settings><con:endpoint>http://monitoring-exp-partner.uk-e1.cloudhub.io</con:endpoint><con:request/><con:originalUri>http://monitoring-exp-partner.uk-e1.cloudhub.io/api/getCustomer</con:originalUri><con:credentials><con:authType>No Authorization</con:authType></con:credentials><con:jmsConfig JMSDeliveryMode="PERSISTENT"/><con:jmsPropertyConfig/><con:parameters><entry key="customerId" value="1" xmlns="http://eviware.com/soapui/config"/></con:parameters><con:parameterOrder><con:entry>customerId</con:entry></con:parameterOrder></con:request><con:request name="PARTNER New ERROR" id="45855003-36bb-4866-9205-c0e1a9114d6b" mediaType="application/json"><con:settings><con:setting id="com.eviware.soapui.impl.wsdl.WsdlRequest@request-headers">&lt;xml-fragment xmlns:con="http://eviware.com/soapui/config">
  &lt;con:entry key="client_id" value="f6d0574deabf4c5e909dbfbb99208ec8"/>
  &lt;con:entry key="client_secret" value="55640ba4007a466AaC7b49Db69E79aE3"/>
&lt;/xml-fragment></con:setting></con:settings><con:endpoint>http://monitoring-exp-partner.uk-e1.cloudhub.io</con:endpoint><con:request/><con:originalUri>http://monitoring-exp-partner.uk-e1.cloudhub.io/api/getCustomer</con:originalUri><con:credentials><con:authType>No Authorization</con:authType></con:credentials><con:jmsConfig JMSDeliveryMode="PERSISTENT"/><con:jmsPropertyConfig/><con:parameters><entry key="customerId" value="ccc" xmlns="http://eviware.com/soapui/config"/></con:parameters><con:parameterOrder><con:entry>customerId</con:entry></con:parameterOrder></con:request></con:method></con:resource></con:interface><con:interface xsi:type="con:RestService" id="e96f3611-7df1-4ec9-9540-cddcc99e420e" wadlVersion="http://wadl.dev.java.net/2009/02" name="http://monitoring-exp-mobile.uk-e1.cloudhub.io" type="rest" xmlns:xsi="http://www.w3.org/2001/XMLSchema-instance"><con:settings/><con:definitionCache/><con:endpoints><con:endpoint>http://monitoring-exp-mobile.uk-e1.cloudhub.io</con:endpoint></con:endpoints><con:resource name="GetCustomer" path="/api/getCustomer" id="0e698e3d-a249-453b-a305-381f33c6441e"><con:settings/><con:parameters><con:parameter><con:name>customerId</con:name><con:value>1</con:value><con:style>QUERY</con:style><con:default>1</con:default><con:path xsi:nil="true"/><con:description xsi:nil="true"/></con:parameter></con:parameters><con:method name="MOBILE GetCustomer 1" id="ec8b3232-6170-4896-93d8-5ab9222df068" method="GET"><con:settings/><con:parameters/><con:representation type="FAULT"><con:mediaType>application/json; charset=UTF-8</con:mediaType><con:status>401</con:status><con:params/><con:element xmlns:get="http://monitoring-exp-mobile.uk-e1.cloudhub.io/api/getCustomer">get:Fault</con:element></con:representation><con:representation type="RESPONSE"><con:mediaType>application/json</con:mediaType><con:status>200</con:status><con:params/><con:element>Response</con:element></con:representation><con:request name="MOBILE OK" id="b96694b4-ef5a-4966-8172-c4a5f2d61f7a" mediaType="application/json"><con:settings><con:setting id="com.eviware.soapui.impl.wsdl.WsdlRequest@request-headers">&lt;xml-fragment xmlns:con="http://eviware.com/soapui/config">
  &lt;con:entry key="client_id" value="d070a2acfd2f48ecaf3647c65708e4f6"/>
  &lt;con:entry key="client_secret" value="EF8391A7e8174fE9979d7b9940a5498a"/>
&lt;/xml-fragment></con:setting></con:settings><con:endpoint>http://monitoring-exp-mobile.uk-e1.cloudhub.io</con:endpoint><con:request/><con:originalUri>http://monitoring-exp-mobile.uk-e1.cloudhub.io/api/getCustomer</con:originalUri><con:credentials><con:authType>No Authorization</con:authType></con:credentials><con:jmsConfig JMSDeliveryMode="PERSISTENT"/><con:jmsPropertyConfig/><con:parameters><entry key="customerId" value="1" xmlns="http://eviware.com/soapui/config"/></con:parameters><con:parameterOrder><con:entry>customerId</con:entry></con:parameterOrder></con:request></con:method><con:method name="MOBILE GetCustomer 1 ATTACK" id="ec8b3232-6170-4896-93d8-5ab9222df068" method="GET"><con:settings/><con:parameters/><con:representation type="FAULT"><con:mediaType>application/json; charset=UTF-8</con:mediaType><con:status>401</con:status><con:params/><con:element xmlns:get="http://monitoring-exp-mobile.uk-e1.cloudhub.io/api/getCustomer">get:Fault</con:element></con:representation><con:request name="MOBILE ATTACK" id="b96694b4-ef5a-4966-8172-c4a5f2d61f7a" mediaType="application/json"><con:settings><con:setting id="com.eviware.soapui.impl.wsdl.WsdlRequest@request-headers">&lt;xml-fragment/></con:setting></con:settings><con:endpoint>http://monitoring-exp-mobile.uk-e1.cloudhub.io</con:endpoint><con:request/><con:originalUri>http://monitoring-exp-mobile.uk-e1.cloudhub.io/api/getCustomer</con:originalUri><con:credentials><con:authType>No Authorization</con:authType></con:credentials><con:jmsConfig JMSDeliveryMode="PERSISTENT"/><con:jmsPropertyConfig/><con:parameters><entry key="customerId" value="1" xmlns="http://eviware.com/soapui/config"/></con:parameters><con:parameterOrder><con:entry>customerId</con:entry></con:parameterOrder></con:request></con:method></con:resource></con:interface><con:interface xsi:type="con:RestService" id="37905049-6f57-400a-a918-19636f710612" wadlVersion="http://wadl.dev.java.net/2009/02" name="http://monitoringdemo-process-order.uk-e1.cloudhub.io" type="rest" xmlns:xsi="http://www.w3.org/2001/XMLSchema-instance"><con:settings/><con:definitionCache/><con:endpoints><con:endpoint>http://monitoringdemo-process-order.uk-e1.cloudhub.io</con:endpoint></con:endpoints><con:resource name="DoOrder" path="/api/doOrder" id="162b5334-5361-4acb-8b6e-2736d8c5b260"><con:settings/><con:parameters><con:parameter><con:name>customerId</con:name><con:value>1</con:value><con:style>QUERY</con:style><con:default>1</con:default><con:path xsi:nil="true"/><con:description xsi:nil="true"/></con:parameter><con:parameter><con:name>orderId</con:name><con:value>1</con:value><con:style>QUERY</con:style><con:default>1</con:default><con:path xsi:nil="true"/><con:description xsi:nil="true"/></con:parameter><con:parameter><con:name>price</con:name><con:value>10</con:value><con:style>QUERY</con:style><con:default>10</con:default><con:path xsi:nil="true"/><con:description xsi:nil="true"/></con:parameter><con:parameter><con:name>newQueryParameter</con:name><con:value>Example</con:value><con:style>QUERY</con:style><con:default>Example</con:default><con:path xsi:nil="true"/><con:description xsi:nil="true"/></con:parameter></con:parameters><con:method name="DoOrder 1" id="45ef3eec-41c1-4e9c-85b6-86bc4681e90e" method="GET"><con:settings/><con:parameters/><con:request name="Request 1" id="aa61cbd4-0f0f-46d5-a6e6-65f6b71aaca3" mediaType="application/json"><con:settings/><con:endpoint>http://monitoringdemo-process-order.uk-e1.cloudhub.io</con:endpoint><con:request/><con:credentials><con:authType>No Authorization</con:authType></con:credentials><con:jmsConfig JMSDeliveryMode="PERSISTENT"/><con:jmsPropertyConfig/><con:parameters>
  <con:entry key="orderId" value="1"/>
  <con:entry key="price" value="10"/>
  <con:entry key="customerId" value="1"/>
  <con:entry key="newQueryParameter" value="Example"/>
</con:parameters><con:parameterOrder><con:entry>customerId</con:entry><con:entry>orderId</con:entry><con:entry>price</con:entry><con:entry>newQueryParameter</con:entry></con:parameterOrder></con:request></con:method></con:resource></con:interface><con:testSuite id="771b83b9-3277-44e1-aab7-689f0d4d468c" name="2_MOBILE ATTACK"><con:settings/><con:runType>SEQUENTIAL</con:runType><con:testCase id="1742fa05-e156-432b-b355-5909b2d06708" failOnError="true" failTestCaseOnErrors="true" keepSession="false" maxResults="0" name="MOBILE ATTACK" searchProperties="true"><con:settings/><con:testStep type="restrequest" name="MOBILE GetCustomer 1 ATTACK - MOBILE ATTACK" id="692aa28f-fef0-479c-b6b9-bd8f4841b97c"><con:settings/><con:config service="http://monitoring-exp-mobile.uk-e1.cloudhub.io" resourcePath="/api/getCustomer" methodName="MOBILE GetCustomer 1 ATTACK" xsi:type="con:RestRequestStep" xmlns:xsi="http://www.w3.org/2001/XMLSchema-instance"><con:restRequest name="MOBILE GetCustomer 1 ATTACK - MOBILE ATTACK" id="b96694b4-ef5a-4966-8172-c4a5f2d61f7a" mediaType="application/json"><con:settings><con:setting id="com.eviware.soapui.impl.wsdl.WsdlRequest@request-headers">&lt;xml-fragment/></con:setting></con:settings><con:endpoint>http://monitoring-exp-mobile.uk-e1.cloudhub.io</con:endpoint><con:request/><con:originalUri>http://monitoring-exp-mobile.uk-e1.cloudhub.io/api/getCustomer</con:originalUri><con:credentials><con:authType>No Authorization</con:authType></con:credentials><con:jmsConfig JMSDeliveryMode="PERSISTENT"/><con:jmsPropertyConfig/><con:parameters><entry key="customerId" value="1" xmlns="http://eviware.com/soapui/config"/></con:parameters><con:parameterOrder><con:entry>customerId</con:entry></con:parameterOrder></con:restRequest></con:config></con:testStep><con:loadTest id="c010a7fb-3336-480b-b4de-a62636402515" name="SIMULATE ATTACK"><con:settings><con:setting id="HttpSettings@close-connections">false</con:setting></con:settings><con:threadCount>5</con:threadCount><con:startDelay>0</con:startDelay><con:sampleInterval>250</con:sampleInterval><con:calculateTPSOnTimePassed>true</con:calculateTPSOnTimePassed><con:resetStatisticsOnThreadCountChange>true</con:resetStatisticsOnThreadCountChange><con:historyLimit>-1</con:historyLimit><con:testLimit>350</con:testLimit><con:limitType>TIME</con:limitType><con:loadStrategy><con:type>Simple</con:type></con:loadStrategy><con:assertion type="Step Status" name="Step Status"/><con:maxAssertionErrors>100</con:maxAssertionErrors><con:cancelExcessiveThreads>true</con:cancelExcessiveThreads><con:strategyInterval>500</con:strategyInterval></con:loadTest><con:properties/></con:testCase><con:properties/></con:testSuite><con:testSuite id="160219e4-1394-4559-b594-e3cfebfe0b6c" name="3_PARTNER Distribution"><con:settings/><con:runType>SEQUENTIAL</con:runType><con:testCase id="9083a437-2e2d-42a6-a2be-381a628e45b9" failOnError="true" failTestCaseOnErrors="true" keepSession="false" maxResults="0" name="INJECT PARTNER CALLS for CustomDashBoard" searchProperties="true"><con:settings/><con:testStep type="restrequest" name="GOLD" id="59feeb33-0c61-4a95-8392-4e21244ffe69"><con:settings/><con:config service="http://monitoring-exp-partner.uk-e1.cloudhub.io" resourcePath="/api/getCustomer" methodName="PARTNER GetCustomer 1" xsi:type="con:RestRequestStep" xmlns:xsi="http://www.w3.org/2001/XMLSchema-instance"><con:restRequest name="GOLD" id="45855003-36bb-4866-9205-c0e1a9114d6b" mediaType="application/json"><con:settings><con:setting id="com.eviware.soapui.impl.wsdl.WsdlRequest@request-headers">&lt;xml-fragment xmlns:con="http://eviware.com/soapui/config">
  &lt;con:entry key="client_id" value="e273a6fcccef4979b2afa4493c6e4c1e"/>
  &lt;con:entry key="client_secret" value="4250071BF60840DBbc5feCc8fB486b75"/>
&lt;/xml-fragment></con:setting></con:settings><con:endpoint>http://monitoring-exp-partner.uk-e1.cloudhub.io</con:endpoint><con:request/><con:originalUri>http://monitoring-exp-partner.uk-e1.cloudhub.io/api/getCustomer</con:originalUri><con:credentials><con:authType>No Authorization</con:authType></con:credentials><con:jmsConfig JMSDeliveryMode="PERSISTENT"/><con:jmsPropertyConfig/><con:parameters><entry key="customerId" value="1" xmlns="http://eviware.com/soapui/config"/></con:parameters><con:parameterOrder><con:entry>customerId</con:entry></con:parameterOrder></con:restRequest></con:config></con:testStep><con:testStep type="restrequest" name="FREE" id="d8ecfb5a-1914-488f-b555-19a0bc8f4cd7"><con:settings/><con:config service="http://monitoring-exp-partner.uk-e1.cloudhub.io" resourcePath="/api/getCustomer" methodName="PARTNER GetCustomer 1" xsi:type="con:RestRequestStep" xmlns:xsi="http://www.w3.org/2001/XMLSchema-instance"><con:restRequest name="FREE" id="45855003-36bb-4866-9205-c0e1a9114d6b" mediaType="application/json"><con:settings><con:setting id="com.eviware.soapui.impl.wsdl.WsdlRequest@request-headers">&lt;xml-fragment xmlns:con="http://eviware.com/soapui/config">
  &lt;con:entry key="client_id" value="05e34f7147f84d2cbab5f2d3004176c6"/>
  &lt;con:entry key="client_secret" value="22c30907f30045218f678738705F5B9A"/>
&lt;/xml-fragment></con:setting></con:settings><con:endpoint>http://monitoring-exp-partner.uk-e1.cloudhub.io</con:endpoint><con:request/><con:originalUri>http://monitoring-exp-partner.uk-e1.cloudhub.io/api/getCustomer</con:originalUri><con:credentials><con:authType>No Authorization</con:authType></con:credentials><con:jmsConfig JMSDeliveryMode="PERSISTENT"/><con:jmsPropertyConfig/><con:parameters><entry key="customerId" value="1" xmlns="http://eviware.com/soapui/config"/></con:parameters><con:parameterOrder><con:entry>customerId</con:entry></con:parameterOrder></con:restRequest></con:config></con:testStep><con:testStep type="restrequest" name="NEW" id="4c275f39-849a-498e-9c07-eb3f87ea4934"><con:settings/><con:config service="http://monitoring-exp-partner.uk-e1.cloudhub.io" resourcePath="/api/getCustomer" methodName="PARTNER GetCustomer 1" xsi:type="con:RestRequestStep" xmlns:xsi="http://www.w3.org/2001/XMLSchema-instance"><con:restRequest name="NEW" id="45855003-36bb-4866-9205-c0e1a9114d6b" mediaType="application/json"><con:settings><con:setting id="com.eviware.soapui.impl.wsdl.WsdlRequest@request-headers">&lt;xml-fragment xmlns:con="http://eviware.com/soapui/config">
  &lt;con:entry key="client_id" value="f6d0574deabf4c5e909dbfbb99208ec8"/>
  &lt;con:entry key="client_secret" value="55640ba4007a466AaC7b49Db69E79aE3"/>
&lt;/xml-fragment></con:setting></con:settings><con:endpoint>http://monitoring-exp-partner.uk-e1.cloudhub.io</con:endpoint><con:request/><con:originalUri>http://monitoring-exp-partner.uk-e1.cloudhub.io/api/getCustomer</con:originalUri><con:credentials><con:authType>No Authorization</con:authType></con:credentials><con:jmsConfig JMSDeliveryMode="PERSISTENT"/><con:jmsPropertyConfig/><con:parameters><entry key="customerId" value="1" xmlns="http://eviware.com/soapui/config"/></con:parameters><con:parameterOrder><con:entry>customerId</con:entry></con:parameterOrder></con:restRequest></con:config></con:testStep><con:testStep type="restrequest" name="GOLD AGAIN" id="34d3c22d-8e05-4c01-8d48-5fc14bf6d62e"><con:settings/><con:config service="http://monitoring-exp-partner.uk-e1.cloudhub.io" resourcePath="/api/getCustomer" methodName="PARTNER GetCustomer 1" xsi:type="con:RestRequestStep" xmlns:xsi="http://www.w3.org/2001/XMLSchema-instance"><con:restRequest name="GOLD AGAIN" id="45855003-36bb-4866-9205-c0e1a9114d6b" mediaType="application/json"><con:settings><con:setting id="com.eviware.soapui.impl.wsdl.WsdlRequest@request-headers">&lt;xml-fragment xmlns:con="http://eviware.com/soapui/config">
  &lt;con:entry key="client_id" value="e273a6fcccef4979b2afa4493c6e4c1e"/>
  &lt;con:entry key="client_secret" value="4250071BF60840DBbc5feCc8fB486b75"/>
&lt;/xml-fragment></con:setting></con:settings><con:endpoint>http://monitoring-exp-partner.uk-e1.cloudhub.io</con:endpoint><con:request/><con:originalUri>http://monitoring-exp-partner.uk-e1.cloudhub.io/api/getCustomer</con:originalUri><con:credentials><con:authType>No Authorization</con:authType></con:credentials><con:jmsConfig JMSDeliveryMode="PERSISTENT"/><con:jmsPropertyConfig/><con:parameters><entry key="customerId" value="1" xmlns="http://eviware.com/soapui/config"/></con:parameters><con:parameterOrder><con:entry>customerId</con:entry></con:parameterOrder></con:restRequest></con:config></con:testStep><con:loadTest id="503e36a8-2ac3-4f7b-9c48-d91f2d0a5264" name="Inject Calls"><con:settings><con:setting id="HttpSettings@close-connections">false</con:setting></con:settings><con:threadCount>5</con:threadCount><con:startDelay>0</con:startDelay><con:sampleInterval>250</con:sampleInterval><con:calculateTPSOnTimePassed>true</con:calculateTPSOnTimePassed><con:resetStatisticsOnThreadCountChange>true</con:resetStatisticsOnThreadCountChange><con:historyLimit>-1</con:historyLimit><con:testLimit>60</con:testLimit><con:limitType>TIME</con:limitType><con:loadStrategy><con:type>Simple</con:type></con:loadStrategy><con:assertion type="Step Status" name="Step Status"/><con:maxAssertionErrors>100</con:maxAssertionErrors><con:cancelExcessiveThreads>true</con:cancelExcessiveThreads><con:strategyInterval>500</con:strategyInterval></con:loadTest><con:properties/></con:testCase><con:properties/></con:testSuite><con:testSuite id="06612357-c99a-473c-8f80-1a2eda51dcd1" name="1_PARTNER NEW ERROR"><con:settings/><con:runType>SEQUENTIAL</con:runType><con:testCase id="46efa8c1-997f-496b-aff9-8307d47c43b5" failOnError="true" failTestCaseOnErrors="true" keepSession="false" maxResults="0" name="Send ERRORs" searchProperties="true"><con:settings/><con:testStep type="restrequest" name="REST Request" id="f69dfb58-1bb4-4a63-8842-6101a884020e"><con:settings/><con:config service="http://monitoring-exp-partner.uk-e1.cloudhub.io" resourcePath="/api/getCustomer" methodName="PARTNER GetCustomer 1" xsi:type="con:RestRequestStep" xmlns:xsi="http://www.w3.org/2001/XMLSchema-instance"><con:restRequest name="REST Request" id="45855003-36bb-4866-9205-c0e1a9114d6b" mediaType="application/json"><con:settings><con:setting id="com.eviware.soapui.impl.wsdl.WsdlRequest@request-headers">&lt;xml-fragment xmlns:con="http://eviware.com/soapui/config">
  &lt;con:entry key="client_id" value="f6d0574deabf4c5e909dbfbb99208ec8"/>
  &lt;con:entry key="client_secret" value="55640ba4007a466AaC7b49Db69E79aE3"/>
&lt;/xml-fragment></con:setting></con:settings><con:endpoint>http://monitoring-exp-partner.uk-e1.cloudhub.io</con:endpoint><con:request/><con:originalUri>http://monitoring-exp-partner.uk-e1.cloudhub.io/api/getCustomer</con:originalUri><con:credentials><con:authType>No Authorization</con:authType></con:credentials><con:jmsConfig JMSDeliveryMode="PERSISTENT"/><con:jmsPropertyConfig/><con:parameters><entry key="customerId" value="ccc" xmlns="http://eviware.com/soapui/config"/></con:parameters><con:parameterOrder><con:entry>customerId</con:entry></con:parameterOrder></con:restRequest></con:config></con:testStep><con:loadTest id="9c7c2337-d1bc-4726-ab47-1863e89831fc" name="INJECT ERRORS"><con:settings><con:setting id="HttpSettings@close-connections">false</con:setting></con:settings><con:threadCount>5</con:threadCount><con:startDelay>0</con:startDelay><con:sampleInterval>250</con:sampleInterval><con:calculateTPSOnTimePassed>true</con:calculateTPSOnTimePassed><con:resetStatisticsOnThreadCountChange>true</con:resetStatisticsOnThreadCountChange><con:historyLimit>-1</con:historyLimit><con:testLimit>310</con:testLimit><con:limitType>TIME</con:limitType><con:loadStrategy><con:type>Simple</con:type></con:loadStrategy><con:assertion type="Step Status" name="Step Status"/><con:maxAssertionErrors>100</con:maxAssertionErrors><con:cancelExcessiveThreads>true</con:cancelExcessiveThreads><con:strategyInterval>500</con:strategyInterval></con:loadTest><con:properties/></con:testCase><con:properties/></con:testSuite><con:testSuite id="a776eb5b-ed0d-4ee0-83e5-99369b627a2a" name="4_PARTNER ORDER"><con:settings/><con:runType>SEQUENTIAL</con:runType><con:testCase id="8c18d009-4efc-4aae-9bec-8aeaf8d33e81" failOnError="true" failTestCaseOnErrors="true" keepSession="false" maxResults="0" name="Inject Orders" searchProperties="true"><con:settings/><con:testStep type="restrequest" name="DoOrder 1 - Request 1" id="01b73d4e-655c-4af4-b837-f344dcf2a2b5"><con:settings/><con:config service="http://monitoringdemo-process-order.uk-e1.cloudhub.io" resourcePath="/api/doOrder" methodName="DoOrder 1" xsi:type="con:RestRequestStep" xmlns:xsi="http://www.w3.org/2001/XMLSchema-instance"><con:restRequest name="DoOrder 1 - Request 1" id="aa61cbd4-0f0f-46d5-a6e6-65f6b71aaca3" mediaType="application/json"><con:settings/><con:endpoint>http://monitoringdemo-process-order.uk-e1.cloudhub.io</con:endpoint><con:request/><con:credentials><con:authType>No Authorization</con:authType></con:credentials><con:jmsConfig JMSDeliveryMode="PERSISTENT"/><con:jmsPropertyConfig/><con:parameters>
  <con:entry key="orderId" value="1"/>
  <con:entry key="price" value="10"/>
  <con:entry key="customerId" value="1"/>
  <con:entry key="newQueryParameter" value="Example"/>
</con:parameters><con:parameterOrder><con:entry>customerId</con:entry><con:entry>orderId</con:entry><con:entry>price</con:entry><con:entry>newQueryParameter</con:entry></con:parameterOrder></con:restRequest></con:config></con:testStep><con:loadTest id="e472ff85-b1ad-458c-b1b1-8dd40f40af8c" name="Inject Orders"><con:settings><con:setting id="HttpSettings@close-connections">false</con:setting></con:settings><con:threadCount>5</con:threadCount><con:startDelay>0</con:startDelay><con:sampleInterval>250</con:sampleInterval><con:calculateTPSOnTimePassed>true</con:calculateTPSOnTimePassed><con:resetStatisticsOnThreadCountChange>true</con:resetStatisticsOnThreadCountChange><con:historyLimit>-1</con:historyLimit><con:testLimit>60</con:testLimit><con:limitType>TIME</con:limitType><con:loadStrategy><con:type>Simple</con:type></con:loadStrategy><con:assertion type="Step Status" name="Step Status"/><con:maxAssertionErrors>100</con:maxAssertionErrors><con:cancelExcessiveThreads>true</con:cancelExcessiveThreads><con:strategyInterval>500</con:strategyInterval></con:loadTest><con:properties/></con:testCase><con:properties/></con:testSuite><con:properties/><con:wssContainer/><con:oAuth2ProfileContainer/><con:oAuth1ProfileContainer/><con:sensitiveInformation/></con:soapui-project>